ptl/__init__.py
ptl/__main__.py
ptl/_error.py
ptl/cli.py
ptl/compat.py
ptl/config.py
ptl/exceptions.py
ptl/infile.py
ptl/layer.py
ptl/providers.py
ptl/py.typed
ptl/utils.py
ptl/commands/__init__.py
ptl/commands/compile.py
ptl/commands/show.py
ptl/commands/sync.py
ptl-0.3.0.dist-info/LICENSE
ptl-0.3.0.dist-info/METADATA
ptl-0.3.0.dist-info/WHEEL
ptl-0.3.0.dist-info/entry_points.txt
ptl-0.3.0.dist-info/top_level.txt
ptl-0.3.0.dist-info/zip-safe
ptl-0.3.0.dist-info/RECORD
