Metadata-Version: 2.1
Name: ptl
Version: 0.3.0
Summary: pip-tools, layered
Author-email: Dmitry Meyer <me@undef.im>
License: MIT
Project-URL: Homepage, https://github.com/un-def/ptl
Project-URL: Repository, https://github.com/un-def/ptl.git
Project-URL: Changelog, https://github.com/un-def/ptl/blob/master/CHANGELOG.md
Project-URL: Issues, https://github.com/un-def/ptl/issues
Classifier: Development Status :: 4 - Beta
Classifier: License :: OSI Approved :: MIT License
Classifier: Operating System :: POSIX :: Linux
Classifier: Intended Audience :: Developers
Classifier: Topic :: Utilities
Classifier: Programming Language :: Python :: 3
Classifier: Programming Language :: Python :: 3 :: Only
Classifier: Programming Language :: Python :: 3.8
Classifier: Programming Language :: Python :: 3.9
Classifier: Programming Language :: Python :: 3.10
Classifier: Programming Language :: Python :: 3.11
Classifier: Programming Language :: Python :: 3.12
Requires-Python: >=3.8
License-File: LICENSE
Provides-Extra: toml
Requires-Dist: tomli; python_version < "3.11" and extra == "toml"
